janky/__init__.py
janky/fixtures.py
janky-0.1.1.dist-info/LICENSE
janky-0.1.1.dist-info/METADATA
janky-0.1.1.dist-info/WHEEL
janky-0.1.1.dist-info/top_level.txt
janky-0.1.1.dist-info/RECORD
