Metadata-Version: 2.1
Name: janky
Version: 0.1.1
Summary: null
Author: Katie McLaughlin
License: Apache-2.0
Project-URL: Homepage, https://github.com/glasnt/janky
Project-URL: Changelog, https://github.com/glasnt/janky/releases
Project-URL: Issues, https://github.com/glasnt/janky/issues
Project-URL: CI, https://github.com/glasnt/janky/actions
Classifier: License :: OSI Approved :: Apache Software License
Requires-Python: >=3.10
License-File: LICENSE
Requires-Dist: grapheme
Provides-Extra: test
Requires-Dist: pytest ; extra == 'test'
